{
    "LAST_UPDATED": "2026-04-02T02:09:17.553480+00:00",
    "PHX": {
        "last_updated": "2026-04-02T02:09:17.553480+00:00",
        "data": [
            {
                "name": "T3 General",
                "waitMinutes": 9
            },
            {
                "name": "T4 Checkpoint A General",
                "waitMinutes": 13
            },
            {
                "name": "T4 Checkpoint B General",
                "waitMinutes": 8
            },
            {
                "name": "T4 Checkpoint C General",
                "waitMinutes": 8
            },
            {
                "name": "T4 Checkpoint D General",
                "waitMinutes": 7
            }
        ]
    },
    "LAX": {
        "last_updated": "2026-04-02T02:09:17.553480+00:00",
        "data": [
            {
                "name": "All Terminals",
                "waitMinutes": "4"
            },
            {
                "name": "Terminal Tom Bradley General",
                "waitMinutes": "5"
            },
            {
                "name": "Terminal Tom Bradley TSA PreCheck",
                "waitMinutes": "2"
            }
        ]
    },
    "IAD": {
        "last_updated": "2026-04-02T02:09:17.553480+00:00",
        "data": [
            {
                "name": "Terminals",
                "waitMinutes": "4"
            }
        ]
    },
    "IAH": {
        "last_updated": "2026-04-02T02:09:17.553480+00:00",
        "data": [
            {
                "name": "All Terminals",
                "waitMinutes": "8"
            },
            {
                "name": "Terminal A",
                "waitMinutes": "8"
            },
            {
                "name": "Terminal E",
                "waitMinutes": "9"
            }
        ]
    },
    "LGA": {
        "last_updated": "2026-04-02T02:09:17.553480+00:00",
        "data": [
            {
                "name": "All Terminals",
                "waitMinutes": "2"
            },
            {
                "name": "Terminal A",
                "waitMinutes": "3"
            },
            {
                "name": "Terminal B",
                "waitMinutes": "1"
            },
            {
                "name": "Terminal C",
                "waitMinutes": "2"
            }
        ]
    },
    "ATL": {
        "last_updated": "2026-04-02T02:09:17.553480+00:00",
        "data": [
            {
                "name": "All Terminals",
                "waitMinutes": "8"
            }
        ]
    },
    "MIA": {
        "last_updated": "2026-04-02T02:09:17.553480+00:00",
        "data": [
            {
                "name": "All Terminals",
                "waitMinutes": "3"
            },
            {
                "name": "Terminal Checkpoint 3 Priority",
                "waitMinutes": "0"
            },
            {
                "name": "Terminal Checkpoint 4 Priority",
                "waitMinutes": "0"
            }
        ]
    },
    "DEN": {
        "last_updated": "2026-04-02T02:09:17.553480+00:00",
        "data": [
            {
                "name": "All Terminals",
                "waitMinutes": "0"
            },
            {
                "name": "Terminal East Security",
                "waitMinutes": "0"
            },
            {
                "name": "Terminal West Security",
                "waitMinutes": "0"
            }
        ]
    },
    "ORD": {
        "last_updated": "2026-04-02T02:09:17.553480+00:00",
        "data": [
            {
                "name": "All Terminals",
                "waitMinutes": "2"
            },
            {
                "name": "Terminal 2 Checkpoint 5 General",
                "waitMinutes": "1"
            },
            {
                "name": "Terminal 2 Checkpoint 5 TSA Pre",
                "waitMinutes": "1"
            },
            {
                "name": "Terminal 3 Checkpoint 6 General",
                "waitMinutes": "1"
            },
            {
                "name": "Terminal 3 Checkpoint 7 General",
                "waitMinutes": "3"
            },
            {
                "name": "Terminal 3 Checkpoint 7 TSA Pre",
                "waitMinutes": "3"
            },
            {
                "name": "Terminal 3 Checkpoint 8 General",
                "waitMinutes": "2"
            },
            {
                "name": "Terminal 3 Checkpoint 8 TSA Pre",
                "waitMinutes": "1"
            },
            {
                "name": "Terminal 3 Checkpoint 9 General",
                "waitMinutes": "0"
            }
        ]
    },
    "CLT": {
        "last_updated": "2026-04-01T23:35:06.300848+00:00",
        "data": [
            {
                "name": "All Terminals",
                "waitMinutes": "5"
            }
        ]
    },
    "BOS": {
        "last_updated": "2026-04-02T02:09:17.553480+00:00",
        "data": [
            {
                "name": "Terminals",
                "waitMinutes": "11"
            }
        ]
    },
    "AUS": {
        "last_updated": "2026-04-02T02:09:17.553480+00:00",
        "data": [
            {
                "name": "Terminals",
                "waitMinutes": "10"
            }
        ]
    },
    "MSY": {
        "last_updated": "2026-04-02T02:09:17.553480+00:00",
        "data": [
            {
                "name": "Terminals",
                "waitMinutes": "3"
            }
        ]
    },
    "OSL": {
        "last_updated": "2026-04-02T02:09:17.553480+00:00",
        "data": []
    },
    "BWI": {
        "last_updated": "2026-04-02T02:09:17.553480+00:00",
        "data": [
            {
                "name": "All Terminals",
                "waitMinutes": "1"
            },
            {
                "name": "Terminal Checkpoint BC General",
                "waitMinutes": "1"
            },
            {
                "name": "Terminal Checkpoint BC Priority",
                "waitMinutes": "1"
            },
            {
                "name": "Terminal Checkpoint DE General",
                "waitMinutes": "1"
            },
            {
                "name": "Terminal Checkpoint DE PreCheck",
                "waitMinutes": "1"
            },
            {
                "name": "Terminal Checkpoint DE Priority",
                "waitMinutes": "1"
            }
        ]
    },
    "RSW": {
        "last_updated": "2026-04-02T02:09:17.553480+00:00",
        "data": [
            {
                "name": "Terminals",
                "waitMinutes": "1"
            }
        ]
    }
}